Workbook
Name \p: #N/A
Name \s: #N/A
Name _____reg12: '[3]Maturity Rpt'!$L$134:$P$135
Name ____L21: '[4]Laser Lease Expense'!$A$2
Name ___CPP1: #REF!
Name ___CPP1: #REF!
Name ___CPP10: #REF!
Name ___CPP10: #REF!
Name ___CPP11: #REF!
Name ___CPP11: #REF!
Name ___CPP12: #REF!
Name ___CPP12: #REF!
Name ___CPP13: #REF!
Name ___CPP13: #REF!
Name ___CPP14: #REF!
Name ___CPP14: #REF!
Name ___CPP15: #REF!
Name ___CPP15: #REF!
Name ___CPP16: #REF!
Name ___CPP16: #REF!
Name ___CPP17: #REF!
Name ___CPP17: #REF!
Name ___CPP18: #REF!
Name ___CPP18: #REF!
Name ___CPP2: #REF!
Name ___CPP2: #REF!
Name ___CPP3: #REF!
Name ___CPP3: #REF!
Name ___CPP4: #REF!
Name ___CPP4: #REF!
Name ___CPP5: #REF!
Name ___CPP5: #REF!
Name ___CPP6: #REF!
Name ___CPP6: #REF!
Name ___CPP7: #REF!
Name ___CPP7: #REF!
Name ___CPP8: #REF!
Name ___CPP8: #REF!
Name ___CPP9: #REF!
Name ___CPP9: #REF!
Name ___L21: '[4]Laser Lease Expense'!$A$2
Name ___MOB1: #REF!
Name ___MOB1: #REF!
Name ___MOB2: #REF!
Name ___MOB2: #REF!
Name ___MOB3: #REF!
Name ___MOB3: #REF!
Name ___MOB4: #REF!
Name ___MOB4: #REF!
Name ___MOB5: #REF!
Name ___MOB5: #REF!
Name ___MOB6: #REF!
Name ___MOB6: #REF!
Name ___MOB7: #REF!
Name ___MOB7: #REF!
Name ___MOB8: #REF!
Name ___MOB8: #REF!
Name ___MOB9: #REF!
Name ___MOB9: #REF!
Name ___PP1: #REF!

Sheet OS Report
B1: 2726 | C1: 000 | E1: OS | F1: Check to TB | H1: BFC | I1: Check to TB | K1: Difference
A2: 4100000 - Revenue | B2: 200353943 | C2: =-B2/1000 -> -200353.94 | E2: =SUMIFS('OS TB'!U:U,'OS TB'!V:V,LEFT(A2,3))/1000 -> -200353.94 | F2: =E2-C2 -> 0 | H2: =-SUMIFS('SAP BFC REPORT'!H:H,'SAP BFC REPORT'!J:J,A2) -> -200353 | I2: =H2-C2 -> 0.943 | K2: =H2-E2 -> 0.943
A3: EXP_EXC_DNA - Operating Expense (Ex-D And A) | B3: -174068474 | C3: =-B3/1000 -> 174068.47
A4: 5010000 - Cost Of Raw Materials And Supplies | B4: -2651110 | C4: =-B4/1000 -> 2651.11 | E4: =SUMIFS('OS TB'!U:U,'OS TB'!V:V,LEFT(A4,3))/1000 -> 2651.11 | F4: =E4-C4 -> 0 | H4: =-SUMIFS('SAP BFC REPORT'!H:H,'SAP BFC REPORT'!J:J,A4) -> 2651 | I4: =H4-C4 -> -0.11 | K4: =H4-E4 -> -0.11
A5: 5020000 - Staff Costs | B5: -126728921 | C5: =-B5/1000 -> 126728.92 | E5: =SUMIFS('OS TB'!U:U,'OS TB'!V:V,LEFT(A5,3))/1000 -> 126728.92 | F5: =E5-C5 -> 0 | H5: =-SUMIFS('SAP BFC REPORT'!H:H,'SAP BFC REPORT'!J:J,A5) -> 126729 | I5: =H5-C5 -> 0.079 | K5: =H5-E5 -> 0.079
A6: 5030000 - Licence Fees | C6: =-B6/1000 -> 0 | E6: =SUMIFS('OS TB'!U:U,'OS TB'!V:V,LEFT(A6,3))/1000 -> 0 | F6: =E6-C6 -> 0 | H6: =-SUMIFS('SAP BFC REPORT'!H:H,'SAP BFC REPORT'!J:J,A6) -> 0 | I6: =H6-C6 -> 0 | K6: =H6-E6 -> 0
A7: 5050000 - Company Premise Utilities And Maintenance | B7: -19704934 | C7: =-B7/1000 -> 19704.934 | E7: =SUMIFS('OS TB'!U:U,'OS TB'!V:V,LEFT(A7,3))/1000 -> 19704.934 | F7: =E7-C7 -> 0 | H7: =-SUMIFS('SAP BFC REPORT'!H:H,'SAP BFC REPORT'!J:J,A7) -> 19674 | I7: =H7-C7 -> -30.934 | K7: =H7-E7 -> -30.934
A8: 5060000 - Subcontracting services | B8: -4712961 | C8: =-B8/1000 -> 4712.961 | E8: =SUMIFS('OS TB'!U:U,'OS TB'!V:V,LEFT(A8,3))/1000 -> 4712.961 | F8: =E8-C8 -> 0 | H8: =-SUMIFS('SAP BFC REPORT'!H:H,'SAP BFC REPORT'!J:J,A8) -> 4713 | I8: =H8-C8 -> 0.039 | K8: =H8-E8 -> 0.039
A9: 5080000 - Other costs | B9: -20270548 | C9: =-B9/1000 -> 20270.548 | E9: =SUMIFS('OS TB'!U:U,'OS TB'!V:V,LEFT(A9,3))/1000 -> 20270.548 | F9: =E9-C9 -> 0 | H9: =-SUMIFS('SAP BFC REPORT'!H:H,'SAP BFC REPORT'!J:J,A9) -> 20302 | I9: =H9-C9 -> 31.452 | K9: =H9-E9 -> 31.452
A10: Trade_Plug - Interco trade (interco revenue and OPEX) plug | C10: =-B10/1000 -> 0 | F10: =E10-C10 -> 0 | I10: =H10-C10 -> 0
A11: EBITDA | B11: 26285469 | C11: =-B11/1000 -> -26285.469
A12: 5040000 - Depreciation And Amortisation | B12: -6558574 | C12: =-B12/1000 -> 6558.574 | E12: =SUMIFS('OS TB'!U:U,'OS TB'!V:V,LEFT(A12,3))/1000 -> 6558.574 | F12: =E12-C12 -> 0 | H12: =-SUMIFS('SAP BFC REPORT'!H:H,'SAP BFC REPORT'!J:J,A12) -> 6558 | I12: =H12-C12 -> -0.574 | K12: =H12-E12 -> -0.574
A13: EBIT | B13: 19726895 | C13: =-B13/1000 -> -19726.895
A14: 6021000 - Finance Income | B14: 7927600 | C14: =-B14/1000 -> -7927.6 | E14: =SUMIFS('OS TB'!U:U,'OS TB'!V:V,LEFT(A14,3))/1000 -> -7927.6 | F14: =E14-C14 -> 0 | H14: =-SUMIFS('SAP BFC REPORT'!H:H,'SAP BFC REPORT'!J:J,A14) -> -7928 | I14: =H14-C14 -> -0.4 | K14: =H14-E14 -> -0.4
A15: 6031000 - Finance Expense | B15: -11672607 | C15: =-B15/1000 -> 11672.607 | E15: =SUMIFS('OS TB'!U:U,'OS TB'!V:V,LEFT(A15,3))/1000 -> 11672.607 | F15: =E15-C15 -> 0 | H15: =-SUMIFS('SAP BFC REPORT'!H:H,'SAP BFC REPORT'!J:J,A15) -> 11672 | I15: =H15-C15 -> -0.607 | K15: =H15-E15 -> -0.607
A16: Interest_Plug_PL - Interco Interest Receivables And Payables Plug | C16: =-B16/1000 -> 0 | F16: =E16-C16 -> 0 | H16: =-SUMIFS('SAP BFC REPORT'!H:H,'SAP BFC REPORT'!J:J,A16) -> 0 | I16: =H16-C16 -> 0
A17: 8010000 - Share Of Results Of AJV | C17: =-B17/1000 -> 0 | F17: =E17-C17 -> 0 | H17: =-SUMIFS('SAP BFC REPORT'!H:H,'SAP BFC REPORT'!J:J,A17) -> 0 | I17: =H17-C17 -> 0
A18: 6010000 - Non operating gain loss | B18: -309157 | C18: =-B18/1000 -> 309.157 | E18: =SUMIFS('OS TB'!U:U,'OS TB'!V:V,LEFT(A18,3))/1000 -> 309.157 | F18: =E18-C18 -> 0 | H18: =-SUMIFS('SAP BFC REPORT'!H:H,'SAP BFC REPORT'!J:J,A18) -> 309 | I18: =H18-C18 -> -0.157 | K18: =H18-E18 -> -0.157
A19: 6990000 - Exceptional Items | C19: =-B19/1000 -> 0 | F19: =E19-C19 -> 0 | H19: =-SUMIFS('SAP BFC REPORT'!H:H,'SAP BFC REPORT'!J:J,A19) -> 0 | I19: =H19-C19 -> 0
A20: PBT - Profit Or Loss Before Tax | B20: 15672731 | C20: =-B20/1000 -> -15672.731
A21: 6070000 - Income Tax Expense | B21: -3448001 | C21: =-B21/1000 -> 3448.001 | E21: =SUMIFS('OS TB'!U:U,'OS TB'!V:V,LEFT(A21,3))/1000 -> 3448.001 | F21: =E21-C21 -> 0 | H21: =-SUMIFS('SAP BFC REPORT'!H:H,'SAP BFC REPORT'!J:J,A21) -> 3448 | I21: =H21-C21 -> -0.001 | K21: =H21-E21 -> -0.001
A22: 8610000 - Profit Or Loss From Discontinued Operation (Net Of Tax) | C22: =-B22/1000 -> 0 | F22: =E22-C22 -> 0 | I22: =H22-C22 -> 0
A23: PAT - Net Profit Or Loss (PAT) | B23: 12224730 | C23: =-B23/1000 -> -12224.73
A24: PL_MI - Minority Interest | C24: =-B24/1000 -> 0 | F24: =E24-C24 -> 0 | I24: =H24-C24 -> 0
A25: PL_MI_CJE - NCI (CJE) | C25: =-B25/1000 -> 0 | F25: =E25-C25 -> 0 | I25: =H25-C25 -> 0
A26: ATT_OWN - Profit Or Loss Attributable To Owners Of The Company | B26: 12224730 | C26: =-B26/1000 -> -12224.73

Sheet SAP BFC REPORT
H2: 18277
H3: WFS DENMARK
H5: Denmark
B6: WFS CODE | D6: LABEL
B7: 7R0000 | D7: Total Revenue | H7: 200353
B8: 4R6000 | D8: Field Contribution excluding ROU rent cancellations | H8: 53331
B9: 4R4000 | D9: SG&A incl. Interco adjustments & elimination | H9: -17692
B10: 4R3000 | D10: Adjusted EBITDA excluding IFRS16 and Mgt fees/royalties | H10: 35639
B11: 5R0020 | D11: Other operational incomes/expenses
B12: 3R7000 | D12: EBITDA excl. management fees and royalties | H12: 35639
B13: 3R4000 | D13: Depreciation excl ROU & Amortization | H13: -1540
B14: 3R1100 | D14: EBIT excluding IFR16 and Management fees | H14: 34099
B15: 3R3000 | D15: Depreciation ROU&Concession | H15: -5018
B16: 3R8000 | D16: ROU Rental cancellations
B17: 3R1000 | D17: EBIT excl. management fees and royalties | H17: 29081
B18: 2R9000 | D18: Management fees and royalties | H18: -9263
B19: 2R0000 | D19: Operating Result | H19: 19818
B20: 2R0080 | D20: Share of profit/loss of associates
B21: 2R0050B | D21: Non Operating Income/ Expenses | H21: -309
B22: 2R6000 | D22: Interest expenses excluding ROU interests including Interco adjustments & elimination | H22: 7345
B23: 2R5000 | D23: Interest ROU and Concession | H23: -11089
B24: 7R0430 | D24: Exchange rate Gain / Loss | H24: -92
B25: 2R3000 | D25: PBT | H25: 15673
B26: 2R2000 | D26: Current Income Tax | H26: -3448
B27: 7R0630 | D27: Deferred income tax
B28: 2R0070 | D28: Minority interests in Profit or Loss
B29: 1R0000 | D29: Net Result | H29: 12225
B33: 1R0020 | D33: Adjusted EBITDA excluding all Service fees | H33: 35639
B35: CONTROL | D35: EBITDA | H35: 0
B38: SATS SUBTOT | D38: LABEL
B39: S-REVENUE | D39: Revenue | H39: 200353
D40: Operating expenses | H40: -171023
B41: S-EMPLOYMT | D41: Employement costs | H41: -126729
B42: S-DAP | D42: Depreciation and amortisation | H42: -6558
B43: S-LICENCE | D43: License fees
B44: S-UTILITY | D44: Company premise, utilities and maintenance | H44: -11470
B45: S-SUBCONTRCT | D45: Subcontracting Services | H45: -4713
B46: S-SUPPLY | D46: Cost of Raw Material and Supplies | H46: -2651
B47: S-OTHERCOST | D47: Other costs | H47: -18902
D48: Operating profit excl. Mgt fees/royalties | H48: 29330
B49: S-SERVICEFEE | D49: Management fees and royalties | H49: -9512
D50: Operating Profit | H50: 19818
B51: S-JV | D51: Shares of associates's Profit
B52: S-FINFXGL | D52: Gain/(Loss) on Exchange (Financial) | H52: -92
B53: S-FINANCE | D53: Net finance income/(exp) | H53: -3744
B54: S-NONOPERAT | D54: Non-operating income/(exp) | H54: -309
D55: Profit/losses before taxes | H55: 15673
B56: S-TAX | D56: Taxes | H56: -3448
D57: Profit / losses after taxes | H57: 12225
B58: S-MI | D58: Minority interests
D59: Profit after taxes and minority interests | H59: 12225
I61: =IF(B61="","",SUMIFS('TB BFC'!$Z:$Z,'TB BFC'!$E:$E,B61)-H61)
B62: WFS ACCNT | D62: WFS LABEL | E62: SATS ACCNT | F62: SATS SUBTOTAL
B64: 9R0010 | D64: Cargo Import | E64: 41001010 | F64: S-REVENUE | H64: 30120 | I64: =IF(OR(B64="",E64=""),"",SUMIFS('TB BFC'!$Z:$Z,'TB BFC'!$E:$E,B64)-H64) -> 0.33914 | J64: =VLOOKUP(B64,'OS to BFC L2 Mapping'!A:B,2,0) -> 4100000 - Revenue
B65: 9R0011 | D65: Cargo Export | E65: 41001010 | F65: S-REVENUE | H65: 58140 | I65: =IF(OR(B65="",E65=""),"",SUMIFS('TB BFC'!$Z:$Z,'TB BFC'!$E:$E,B65)-H65) -> 0.0624 | J65: =VLOOKUP(B65,'OS to BFC L2 Mapping'!A:B,2,0) -> 4100000 - Revenue
B66: 9R00121 | D66: THC, ISC | E66: 41001010 | F66: S-REVENUE | H66: 88867 | I66: =IF(OR(B66="",E66=""),"",SUMIFS('TB BFC'!$Z:$Z,'TB BFC'!$E:$E,B66)-H66) -> -0.08386 | J66: =VLOOKUP(B66,'OS to BFC L2 Mapping'!A:B,2,0) -> 4100000 - Revenue
B67: 9R00122 | D67: Storage | E67: 41001010 | F67: S-REVENUE | H67: 15120 | I67: =IF(OR(B67="",E67=""),"",SUMIFS('TB BFC'!$Z:$Z,'TB BFC'!$E:$E,B67)-H67) -> -0.398 | J67: =VLOOKUP(B67,'OS to BFC L2 Mapping'!A:B,2,0) -> 4100000 - Revenue
B68: 8R0010 | D68: Cargo Handling | H68: 192247 | I68: =IF(OR(B68="",E68=""),"",SUMIFS('TB BFC'!$Z:$Z,'TB BFC'!$E:$E,B68)-H68) | J68: =VLOOKUP(B68,'OS to BFC L2 Mapping'!A:B,2,0) -> 0
B69: 8R0012 | D69: Security Taxes | E69: 41001010 | F69: S-REVENUE | H69: 5648 | I69: =IF(OR(B69="",E69=""),"",SUMIFS('TB BFC'!$Z:$Z,'TB BFC'!$E:$E,B69)-H69) -> 0.44715 | J69: =VLOOKUP(B69,'OS to BFC L2 Mapping'!A:B,2,0) -> 4100000 - Revenue
B70: 8R0013 | D70: Baggage | E70: 41001010 | F70: S-REVENUE | H70: 181 | I70: =IF(OR(B70="",E70=""),"",SUMIFS('TB BFC'!$Z:$Z,'TB BFC'!$E:$E,B70)-H70) -> 0.45505 | J70: =VLOOKUP(B70,'OS to BFC L2 Mapping'!A:B,2,0) -> 4100000 - Revenue
B71: 8R0017 | D71: Building Rental Revenue | E71: 41001010 | F71: S-REVENUE | H71: 1254 | I71: =IF(OR(B71="",E71=""),"",SUMIFS('TB BFC'!$Z:$Z,'TB BFC'!$E:$E,B71)-H71) -> 0.43916 | J71: =VLOOKUP(B71,'OS to BFC L2 Mapping'!A:B,2,0) -> 4100000 - Revenue
B72: 8R0020 | D72: Other Revenue | E72: 41001010 | F72: S-REVENUE | H72: 2499 | I72: =IF(OR(B72="",E72=""),"",SUMIFS('TB BFC'!$Z:$Z,'TB BFC'!$E:$E,B72)-H72) -> -0.0976 | J72: =VLOOKUP(B72,'OS to BFC L2 Mapping'!A:B,2,0) -> 4100000 - Revenue
B73: 8R0021 | D73: Rebates | E73: 41003020 | F73: S-REVENUE | H73: -1476 | I73: =IF(OR(B73="",E73=""),"",SUMIFS('TB BFC'!$Z:$Z,'TB BFC'!$E:$E,B73)-H73) -> -0.22146 | J73: =VLOOKUP(B73,'OS to BFC L2 Mapping'!A:B,2,0) -> 4100000 - Revenue
B74: 7R0000 | D74: Total Revenue | H74: 200353 | I74: =IF(OR(B74="",E74=""),"",SUMIFS('[1]Import BFC'!$Z:$Z,'[1]Import BFC'!$E:$E,B74)-H74) | J74: =VLOOKUP(B74,'OS to BFC L2 Mapping'!A:B,2,0) -> 0
I75: =IF(OR(B75="",E75=""),"",SUMIFS('TB BFC'!$Z:$Z,'TB BFC'!$E:$E,B75)-H75) | J75: =VLOOKUP(B75,'OS to BFC L2 Mapping'!A:B,2,0) -> 0
B76: 9R1110FD | D76: Gross Salaries - Field | E76: 50201010 | F76: S-EMPLOYMT | H76: -85236 | I76: =IF(OR(B76="",E76=""),"",SUMIFS('TB BFC'!$Z:$Z,'TB BFC'!$E:$E,B76)-H76) -> -0.2494 | J76: =VLOOKUP(B76,'OS to BFC L2 Mapping'!A:B,2,0) -> 5020000 - Staff Costs
B77: 9R1130FD | D77: Social Charges on Gross salaries and Bonuses - Field | E77: 50204010 | F77: S-EMPLOYMT | H77: -2011 | I77: =IF(OR(B77="",E77=""),"",SUMIFS('TB BFC'!$Z:$Z,'TB BFC'!$E:$E,B77)-H77) -> -0.11485 | J77: =VLOOKUP(B77,'OS to BFC L2 Mapping'!A:B,2,0) -> 5020000 - Staff Costs
B78: 9R1150FD | D78: Retirement expenses - Field | E78: 50204410 | F78: S-EMPLOYMT | H78: -13188 | I78: =IF(OR(B78="",E78=""),"",SUMIFS('TB BFC'!$Z:$Z,'TB BFC'!$E:$E,B78)-H78) -> -0.43018 | J78: =VLOOKUP(B78,'OS to BFC L2 Mapping'!A:B,2,0) -> 5020000 - Staff Costs
I79: =IF(OR(B79="",E79=""),"",SUMIFS('TB BFC'!$Z:$Z,'TB BFC'!$E:$E,B79)-H79) | J79: =VLOOKUP(B79,'OS to BFC L2 Mapping'!A:B,2,0) -> 0
B80: 8R0130FD | D80: Temporary labor costs (agencies) - Field | E80: 50219010 | F80: S-EMPLOYMT | I80: =IF(OR(B80="",E80=""),"",SUMIFS('TB BFC'!$Z:$Z,'TB BFC'!$E:$E,B80)-H80) -> 0 | J80: =VLOOKUP(B80,'OS to BFC L2 Mapping'!A:B,2,0) -> 5020000 - Staff Costs
B81: 8R0140FD | D81: Other Personnel costs - Field | E81: 50216040 | F81: S-EMPLOYMT | H81: -2883 | I81: =IF(OR(B81="",E81=""),"",SUMIFS('TB BFC'!$Z:$Z,'TB BFC'!$E:$E,B81)-H81) -> 0.4407 | J81: =VLOOKUP(B81,'OS to BFC L2 Mapping'!A:B,2,0) -> 5020000 - Staff Costs
I82: =IF(OR(B82="",E82=""),"",SUMIFS('TB BFC'!$Z:$Z,'TB BFC'!$E:$E,B82)-H82) | J82: =VLOOKUP(B82,'OS to BFC L2 Mapping'!A:B,2,0) -> 0
B83: 7R0010FD | D83: Personnel costs - Field | H83: -103318 | I83: =IF(OR(B83="",E83=""),"",SUMIFS('TB BFC'!$Z:$Z,'TB BFC'!$E:$E,B83)-H83) | J83: =VLOOKUP(B83,'OS to BFC L2 Mapping'!A:B,2,0) -> 0
B84: 7R0020FD | D84: Training - Field | E84: 50212030 | F84: S-EMPLOYMT | H84: -60 | I84: =IF(OR(B84="",E84=""),"",SUMIFS('TB BFC'!$Z:$Z,'TB BFC'!$E:$E,B84)-H84) -> -0.10795 | J84: =VLOOKUP(B84,'OS to BFC L2 Mapping'!A:B,2,0) -> 5020000 - Staff Costs
B85: 7R0030FD | D85: Travel and Entertainment - Field | E85: 50214010 | F85: S-EMPLOYMT | H85: -37 | I85: =IF(OR(B85="",E85=""),"",SUMIFS('TB BFC'!$Z:$Z,'TB BFC'!$E:$E,B85)-H85) -> 0.35171 | J85: =VLOOKUP(B85,'OS to BFC L2 Mapping'!A:B,2,0) -> 5020000 - Staff Costs
I86: =IF(OR(B86="",E86=""),"",SUMIFS('TB BFC'!$Z:$Z,'TB BFC'!$E:$E,B86)-H86) | J86: =VLOOKUP(B86,'OS to BFC L2 Mapping'!A:B,2,0) -> 0
B87: 8R0410FD | D87: Handling Sub-contracting costs - Field | E87: 50823410 | F87: S-SUBCONTRCT | H87: -691 | I87: =IF(OR(B87="",E87=""),"",SUMIFS('TB BFC'!$Z:$Z,'TB BFC'!$E:$E,B87)-H87) -> -0.21499 | J87: =VLOOKUP(B87,'OS to BFC L2 Mapping'!A:B,2,0) -> 5060000 - Subcontracting services
B88: 8R0420FD | D88: Trucking Sub-contracting costs - Field | E88: 50823410 | F88: S-SUBCONTRCT | H88: -320 | I88: =IF(OR(B88="",E88=""),"",SUMIFS('TB BFC'!$Z:$Z,'TB BFC'!$E:$E,B88)-H88) -> 0.01979 | J88: =VLOOKUP(B88,'OS to BFC L2 Mapping'!A:B,2,0) -> 5060000 - Subcontracting services
B89: 8R0430FD | D89: Security Sub-contracting costs - Field | E89: 50823410 | F89: S-SUBCONTRCT | H89: -3120 | I89: =IF(OR(B89="",E89=""),"",SUMIFS('TB BFC'!$Z:$Z,'TB BFC'!$E:$E,B89)-H89) -> 0.49899 | J89: =VLOOKUP(B89,'OS to BFC L2 Mapping'!A:B,2,0) -> 5060000 - Subcontracting services
B90: 8R0440FD | D90: Other Sub-contracting - Field | E90: 50823410 | F90: S-SUBCONTRCT | H90: -582 | I90: =IF(OR(B90="",E90=""),"",SUMIFS('TB BFC'!$Z:$Z,'TB BFC'!$E:$E,B90)-H90) -> -0.26513 | J90: =VLOOKUP(B90,'OS to BFC L2 Mapping'!A:B,2,0) -> 5060000 - Subcontracting services
B91: 7R0040FD | D91: Sub-contracting - Field | H91: -4713 | I91: =IF(OR(B91="",E91=""),"",SUMIFS('TB BFC'!$Z:$Z,'TB BFC'!$E:$E,B91)-H91) | J91: =VLOOKUP(B91,'OS to BFC L2 Mapping'!A:B,2,0) -> 0
I92: =IF(OR(B92="",E92=""),"",SUMIFS('TB BFC'!$Z:$Z,'TB BFC'!$E:$E,B92)-H92) | J92: =VLOOKUP(B92,'OS to BFC L2 Mapping'!A:B,2,0) -> 0
B93: 7R0050FD | D93: Billing of costs to external customers | I93: =IF(OR(B93="",E93=""),"",SUMIFS('TB BFC'!$Z:$Z,'TB BFC'!$E:$E,B93)-H93) | J93: =VLOOKUP(B93,'OS to BFC L2 Mapping'!A:B,2,0) -> 0
B94: 8R0610FD | D94: Utilities - Field | E94: 50601010 | F94: S-UTILITY | H94: -2322 | I94: =IF(OR(B94="",E94=""),"",SUMIFS('TB BFC'!$Z:$Z,'TB BFC'!$E:$E,B94)-H94) -> -0.46456 | J94: =VLOOKUP(B94,'OS to BFC L2 Mapping'!A:B,2,0) -> 5050000 - Company Premise Utilities And Maintenance
B95: 8R0620FD | D95: Operationnal Supplies (Plastic / Films / Bastings / Paletts…) - Field | E95: 50818410 | F95: S-SUPPLY | H95: -2651 | I95: =IF(OR(B95="",E95=""),"",SUMIFS('TB BFC'!$Z:$Z,'TB BFC'!$E:$E,B95)-H95) -> -0.10956 | J95: =VLOOKUP(B95,'OS to BFC L2 Mapping'!A:B,2,0) -> 5010000 - Cost Of Raw Materials And Supplies
B96: 8R0630FD | D96: Telecom - Field | E96: 50815010 | F96: S-OTHERCOST | H96: -348 | I96: =IF(OR(B96="",E96=""),"",SUMIFS('TB BFC'!$Z:$Z,'TB BFC'!$E:$E,B96)-H96) -> -0.34462 | J96: =VLOOKUP(B96,'OS to BFC L2 Mapping'!A:B,2,0) -> 5080000 - Other costs
B97: 8R0640FD | D97: IT equipment - Field | E97: 50803040 | F97: S-OTHERCOST | H97: -258 | I97: =IF(OR(B97="",E97=""),"",SUMIFS('TB BFC'!$Z:$Z,'TB BFC'!$E:$E,B97)-H97) -> 0.08329 | J97: =VLOOKUP(B97,'OS to BFC L2 Mapping'!A:B,2,0) -> 5080000 - Other costs
B98: 8R0650FD | D98: Office supplies - Field | E98: 50809020 | F98: S-OTHERCOST | H98: -629 | I98: =IF(OR(B98="",E98=""),"",SUMIFS('TB BFC'!$Z:$Z,'TB BFC'!$E:$E,B98)-H98) -> 0.20316 | J98: =VLOOKUP(B98,'OS to BFC L2 Mapping'!A:B,2,0) -> 5080000 - Other costs
B99: 8R0660FD | D99: Other supplies - Field | E99: 50888010 | F99: S-OTHERCOST | H99: -32 | I99: =IF(OR(B99="",E99=""),"",SUMIFS('TB BFC'!$Z:$Z,'TB BFC'!$E:$E,B99)-H99) -> 0.02905 | J99: =VLOOKUP(B99,'OS to BFC L2 Mapping'!A:B,2,0) -> 5080000 - Other costs
B100: 7R0060FD | D100: Supplies & other costs - Field | H100: -6240 | I100: =IF(OR(B100="",E100=""),"",SUMIFS('TB BFC'!$Z:$Z,'TB BFC'!$E:$E,B100)-H100) | J100: =VLOOKUP(B100,'OS to BFC L2 Mapping'!A:B,2,0) -> 0
B101: 8R0710FD | D101: Rental - Facilities / Buildings - Field | E101: 50501010 | F101: S-UTILITY | H101: -3145 | I101: =IF(OR(B101="",E101=""),"",SUMIFS('TB BFC'!$Z:$Z,'TB BFC'!$E:$E,B101)-H101) -> 0.21866 | J101: =VLOOKUP(B101,'OS to BFC L2 Mapping'!A:B,2,0) -> 5050000 - Company Premise Utilities And Maintenance
B102: 8R0720FD | D102: Rental - Ground equipment / Operationnal equipment - Field | E102: 50806010 | F102: S-OTHERCOST | H102: -2437 | I102: =IF(OR(B102="",E102=""),"",SUMIFS('TB BFC'!$Z:$Z,'TB BFC'!$E:$E,B102)-H102) -> -0.47761 | J102: =VLOOKUP(B102,'OS to BFC L2 Mapping'!A:B,2,0) -> 5050000 - Company Premise Utilities And Maintenance
B103: 8R0730FD | D103: Rental - Vehicles - Field | E103: 50806010 | F103: S-OTHERCOST | H103: -51 | I103: =IF(OR(B103="",E103=""),"",SUMIFS('TB BFC'!$Z:$Z,'TB BFC'!$E:$E,B103)-H103) -> 0.40384 | J103: =VLOOKUP(B103,'OS to BFC L2 Mapping'!A:B,2,0) -> 5050000 - Company Premise Utilities And Maintenance
B104: 8R0740FD | D104: Rental - General equipment - Field | E104: 50806020 | F104: S-OTHERCOST | H104: -40 | I104: =IF(OR(B104="",E104=""),"",SUMIFS('TB BFC'!$Z:$Z,'TB BFC'!$E:$E,B104)-H104) -> -0.06914 | J104: =VLOOKUP(B104,'OS to BFC L2 Mapping'!A:B,2,0) -> 5050000 - Company Premise Utilities And Maintenance
B105: 8R0750FD | D105: Other Rentals - Field | H105: -5168 | I105: =IF(OR(B105="",E105=""),"",SUMIFS('TB BFC'!$Z:$Z,'TB BFC'!$E:$E,B105)-H105) | J105: =VLOOKUP(B105,'OS to BFC L2 Mapping'!A:B,2,0) -> #N/A
B106: 9R0751FD | D106: Rentals - low value lease - Field | E106: 50821030 | F106: S-OTHERCOST | H106: -33 | I106: =IF(OR(B106="",E106=""),"",SUMIFS('TB BFC'!$Z:$Z,'TB BFC'!$E:$E,B106)-H106) -> 0.44 | J106: =VLOOKUP(B106,'OS to BFC L2 Mapping'!A:B,2,0) -> 5050000 - Company Premise Utilities And Maintenance
B107: 9R0753FD | D107: Rentals - other costs related to lease - Field | E107: 50806020 | F107: S-OTHERCOST | H107: -5135 | I107: =IF(OR(B107="",E107=""),"",SUMIFS('TB BFC'!$Z:$Z,'TB BFC'!$E:$E,B107)-H107) -> 0.48 | J107: =VLOOKUP(B107,'OS to BFC L2 Mapping'!A:B,2,0) -> 5050000 - Company Premise Utilities And Maintenance
B108: 7R0070FD | D108: Rental - Field | H108: -10841 | I108: =IF(OR(B108="",E108=""),"",SUMIFS('TB BFC'!$Z:$Z,'TB BFC'!$E:$E,B108)-H108) | J108: =VLOOKUP(B108,'OS to BFC L2 Mapping'!A:B,2,0) -> 0
B109: 8R0810FD | D109: Maintenance Facilities - Field | E109: 50502020 | F109: S-UTILITY | H109: -4123 | I109: =IF(OR(B109="",E109=""),"",SUMIFS('TB BFC'!$Z:$Z,'TB BFC'!$E:$E,B109)-H109) -> -0.18276 | J109: =VLOOKUP(B109,'OS to BFC L2 Mapping'!A:B,2,0) -> 5050000 - Company Premise Utilities And Maintenance
B110: 8R0820FD | D110: IT License & maintenance Application - Field | E110: 50803030 | F110: S-OTHERCOST | H110: -512 | I110: =IF(OR(B110="",E110=""),"",SUMIFS('TB BFC'!$Z:$Z,'TB BFC'!$E:$E,B110)-H110) -> 0.21695 | J110: =VLOOKUP(B110,'OS to BFC L2 Mapping'!A:B,2,0) -> 5080000 - Other costs
...

Sheet TB BFC
A1: D_T | B1: D_U | C1: D_P | D1: D_E | E1: D_A | F1: D_M | G1: D_N | H1: D_F | I1: D_S | J1: D_C | K1: D_KH | L1: D_JOB | M1: D_CO | N1: D_CT | O1: D_OG | P1: D_RH | Q1: D_PP | R1: D_CU | S1: D_RE | T1: D_SU | U1: D_DEST | V1: D_MU | W1: D_PMU | X1: D_AIR | Y1: D_CRT | Z1: P_AMOUNT | AA1: P_COMMENT | AB1: LOCAL ACC
A2: ACTUAL | B2: 2025.12 | C2: 2025.12 | D2: 18277 | E2: 7R0020FD | F2: GL | G2: 0LOC0L | J2: DKK | L2: CAH | Z2: -60.10795 | AB2: =_xlfn.XLOOKUP(E2,[2]LOCAL!D:D,[2]LOCAL!H:H) -> 5220
A3: ACTUAL | B3: 2025.12 | C3: 2025.12 | D3: 18277 | E3: 7R0020FIS | F3: GL | G3: 0LOC0L | J3: DKK | L3: CAH | Z3: -2.2256 | AB3: =_xlfn.XLOOKUP(E3,[2]LOCAL!D:D,[2]LOCAL!H:H) -> 567020
A4: ACTUAL | B4: 2025.12 | C4: 2025.12 | D4: 18277 | E4: 7R0020HRS | F4: GL | G4: 0LOC0L | J4: DKK | L4: CAH | Z4: -27.75 | AB4: =_xlfn.XLOOKUP(E4,[2]LOCAL!D:D,[2]LOCAL!H:H) -> 567023
A5: ACTUAL | B5: 2025.12 | C5: 2025.12 | D5: 18277 | E5: 7R0020LES | F5: GL | G5: 0LOC0L | J5: DKK | L5: CAH | Z5: -6.99271 | AB5: =_xlfn.XLOOKUP(E5,[2]LOCAL!D:D,[2]LOCAL!H:H) -> 567025
A6: ACTUAL | B6: 2025.12 | C6: 2025.12 | D6: 18277 | E6: 7R0020OH | F6: GL | G6: 0LOC0L | J6: DKK | L6: CAH | Z6: -17.99442 | AB6: =_xlfn.XLOOKUP(E6,[2]LOCAL!D:D,[2]LOCAL!H:H) -> 567021
A7: ACTUAL | B7: 2025.12 | C7: 2025.12 | D7: 18277 | E7: 7R0020SDS | F7: GL | G7: 0LOC0L | J7: DKK | L7: CAH | Z7: -12.36942 | AB7: =_xlfn.XLOOKUP(E7,[2]LOCAL!D:D,[2]LOCAL!H:H) -> 567019
A8: ACTUAL | B8: 2025.12 | C8: 2025.12 | D8: 18277 | E8: 7R0020SSS | F8: GL | G8: 0LOC0L | J8: DKK | L8: CAH | Z8: -2.5 | AB8: =_xlfn.XLOOKUP(E8,[2]LOCAL!D:D,[2]LOCAL!H:H) -> 567024
A9: ACTUAL | B9: 2025.12 | C9: 2025.12 | D9: 18277 | E9: 7R0030EXS | F9: GL | G9: 0LOC0L | J9: DKK | L9: CAH | Z9: -327.20797 | AB9: =_xlfn.XLOOKUP(E9,[2]LOCAL!D:D,[2]LOCAL!H:H) -> 320026
A10: ACTUAL | B10: 2025.12 | C10: 2025.12 | D10: 18277 | E10: 7R0030FD | F10: GL | G10: 0LOC0L | J10: DKK | L10: CAH | Z10: -36.64829 | AB10: =_xlfn.XLOOKUP(E10,[2]LOCAL!D:D,[2]LOCAL!H:H) -> 320001
A11: ACTUAL | B11: 2025.12 | C11: 2025.12 | D11: 18277 | E11: 7R0030FIS | F11: GL | G11: 0LOC0L | J11: DKK | L11: CAH | Z11: -13.2608 | AB11: =_xlfn.XLOOKUP(E11,[2]LOCAL!D:D,[2]LOCAL!H:H) -> 320020
A12: ACTUAL | B12: 2025.12 | C12: 2025.12 | D12: 18277 | E12: 7R0030HRS | F12: GL | G12: 0LOC0L | J12: DKK | L12: CAH | Z12: -26.84925 | AB12: =_xlfn.XLOOKUP(E12,[2]LOCAL!D:D,[2]LOCAL!H:H) -> 320023
A13: ACTUAL | B13: 2025.12 | C13: 2025.12 | D13: 18277 | E13: 7R0030ITS | F13: GL | G13: 0LOC0L | J13: DKK | L13: CAH | Z13: -7.78692 | AB13: =_xlfn.XLOOKUP(E13,[2]LOCAL!D:D,[2]LOCAL!H:H) -> 320022
... A137: ACTUAL | B137: 2025.12 | C137: 2025.12 | D137: 18277 | E137: 9R3120 | F137: GL | G137: 0LOC0L | J137: DKK | L137: CAH | Z137: -92.78868 | AB137: =_xlfn.XLOOKUP(E137,[2]LOCAL!D:D,[2]LOCAL!H:H) -> 7630
A138: ACTUAL | B138: 2025.12 | C138: 2025.12 | D138: 18277 | E138: A190 | F138: F99 | G138: 0LOC0L | J138: DKK | Z138: 7087.9812 | AB138: =_xlfn.XLOOKUP(E138,[2]LOCAL!D:D,[2]LOCAL!H:H) -> 10060
A139: ACTUAL | B139: 2025.12 | C139: 2025.12 | D139: 18277 | E139: A1908 | F139: F99 | G139: 0LOC0L | J139: DKK | Z139: -7087.9812 | AB139: =_xlfn.XLOOKUP(E139,[2]LOCAL!D:D,[2]LOCAL!H:H) -> 10075
A140: ACTUAL | B140: 2025.12 | C140: 2025.12 | D140: 18277 | E140: A410 | F140: F99 | G140: 0LOC0L | J140: DKK | Z140: 2963.381 | AB140: =_xlfn.XLOOKUP(E140,[2]LOCAL!D:D,[2]LOCAL!H:H) -> 10400
A141: ACTUAL | B141: 2025.12 | C141: 2025.12 | D141: 18277 | E141: A4108 | F141: F99 | G141: 0LOC0L | J141: DKK | Z141: -466.90997 | AB141: =_xlfn.XLOOKUP(E141,[2]LOCAL!D:D,[2]LOCAL!H:H) -> 10430
A142: ACTUAL | B142: 2025.12 | C142: 2025.12 | D142: 18277 | E142: A415 | F142: F99 | G142: 0LOC0L | J142: DKK | Z142: 905.18808 | AB142: =_xlfn.XLOOKUP(E142,[2]LOCAL!D:D,[2]LOCAL!H:H) -> 13200
A143: ACTUAL | B143: 2025.12 | C143: 2025.12 | D143: 18277 | E143: A4158 | F143: F99 | G143: 0LOC0L | J143: DKK | Z143: -331.79016 | AB143: =_xlfn.XLOOKUP(E143,[2]LOCAL!D:D,[2]LOCAL!H:H) -> 13450
A144: ACTUAL | B144: 2025.12 | C144: 2025.12 | D144: 18277 | E144: A425 | F144: F99 | G144: 0LOC0L | J144: DKK | Z144: 9344.3438 | AB144: =_xlfn.XLOOKUP(E144,[2]LOCAL!D:D,[2]LOCAL!H:H) -> 11200
A145: ACTUAL | B145: 2025.12 | C145: 2025.12 | D145: 18277 | E145: A4258 | F145: F99 | G145: 0LOC0L | J145: DKK | Z145: -2818.7237 | AB145: =_xlfn.XLOOKUP(E145,[2]LOCAL!D:D,[2]LOCAL!H:H) -> 11450
A146: ACTUAL | B146: 2025.12 | C146: 2025.12 | D146: 18277 | E146: A491 | F146: F99 | G146: 0LOC0L | J146: DKK | Z146: 196667.14 | AB146: =_xlfn.XLOOKUP(E146,[2]LOCAL!D:D,[2]LOCAL!H:H) -> 13610
A147: ACTUAL | B147: 2025.12 | C147: 2025.12 | D147: 18277 | E147: A4918 | F147: F99 | G147: 0LOC0L | J147: DKK | Z147: -72404.509 | AB147: =_xlfn.XLOOKUP(E147,[2]LOCAL!D:D,[2]LOCAL!H:H) -> 13650
A148: ACTUAL | B148: 2025.12 | C148: 2025.12 | D148: 18277 | E148: A492 | F148: F99 | G148: 0LOC0L | J148: DKK | Z148: 15265.695 | AB148: =_xlfn.XLOOKUP(E148,[2]LOCAL!D:D,[2]LOCAL!H:H) -> 13691
A149: ACTUAL | B149: 2025.12 | C149: 2025.12 | D149: 18277 | E149: A4928 | F149: F99 | G149: 0LOC0L | J149: DKK | Z149: -4697.4852 | AB149: =_xlfn.XLOOKUP(E149,[2]LOCAL!D:D,[2]LOCAL!H:H) -> 13694
... A172: ACTUAL | B172: 2025.12 | C172: 2025.12 | D172: 18277 | E172: P816 | F172: F99 | G172: 0LOC0L | J172: DKK | Z172: 1027.9636 | AB172: =_xlfn.XLOOKUP(E172,[2]LOCAL!D:D,[2]LOCAL!H:H) -> 24271

Sheet ERP TO SAP BFC Mapping

Sheet OS TB
A1: Entities | B1: Scenario | C1: Time | D1: Cons | E1: View | F1: Local COA | G1: SAP COA | H1: SATS_COA | I1: Flow | J1: Origin | K1: IC | L1: LOB | M1: Function | N1: Aviation | O1: Audit | P1: Analysis | Q1: UD6# | R1: UD7# | S1: UD8# | T1: Source Id | U1: Amount
A2: 2708 | F2: 10065 - Additions | G2: A190 | H2: 1521300 | K2: None | T2: 2708_TB | U2: 7087981 | V2: =LEFT(H2,3) -> 152
A3: 2708 | F3: 10075 - Depreciation beginning of the year | G3: A1908 | H3: 1525300 | K3: None | T3: 2708_TB | U3: -7087981 | V3: =LEFT(H3,3) -> 152
A4: 2708 | F4: 1100 - Revenue Cargo DK Import | G4: 9R0010 | H4: 410010102 | K4: None | L4: 3A01 | M4: FLDS | N4: 1 | T4: 2708_TB | U4: -619905 | V4: =LEFT(H4,3) -> 410
A5: 2708 | F5: 1101 - Revenue Cargo DK Export | G5: 9R0011 | H5: 410010104 | K5: None | L5: 3A01 | M5: FLDS | N5: 1 | T5: 2708_TB | U5: 0 | V5: =LEFT(H5,3) -> 410
A6: 2708 | F6: 1110 - Revenue Cargo EU (services) Im | G6: 9R0010 | H6: 410010102 | K6: None | L6: 3A01 | M6: FLDS | N6: 1 | T6: 2708_TB | U6: -34346 | V6: =LEFT(H6,3) -> 410
A7: 2708 | F7: 1111 - Revenue Cargo EU (service) Exp | G7: 9R0011 | H7: 410010104 | K7: None | L7: 3A01 | M7: FLDS | N7: 1 | T7: 2708_TB | U7: -480 | V7: =LEFT(H7,3) -> 410
A8: 2708 | F8: 1120 - Revenue Cargo outside EU (C) I | G8: 9R0010 | H8: 410010102 | K8: None | L8: 3A01 | M8: FLDS | N8: 1 | T8: 2708_TB | U8: -29466088 | V8: =LEFT(H8,3) -> 410
A9: 2708 | F9: 11200 - Costs beginning of the year | G9: A425 | H9: 1500140 | K9: None | T9: 2708_TB | U9: 6782312 | V9: =LEFT(H9,3) -> 150
A10: 2708 | F10: 1121 - Revenue Cargo outside EU (C) E | G10: 9R0011 | H10: 410010104 | K10: None | L10: 3A01 | M10: FLDS | N10: 1 | T10: 2708_TB | U10: -57102409 | V10: =LEFT(H10,3) -> 410
A11: 2708 | F11: 1122 - Revenue Cargo outside EU Export - GSA | G11: 9R0011 | H11: 410010104 | K11: None | L11: 3A01 | M11: FLDS | N11: 1 | T11: 2708_TB | U11: -1037173 | V11: =LEFT(H11,3) -> 410
A12: 2708 | F12: 1130 - Revenue X-ray (forwarders) | G12: 8R0012 | H12: 410030106 | K12: None | L12: 3A01 | M12: FLDS | N12: 1 | T12: 2708_TB | U12: -4664476 | V12: =LEFT(H12,3) -> 410
A13: 2708 | F13: 11300 - Additions | G13: A425 | H13: 1500140 | K13: None | T13: 2708_TB | U13: 3276401 | V13: =LEFT(H13,3) -> 150
A14: 2708 | F14: 1131 - Revenue X-ray (forwarders) EU (Service) | G14: 8R0012 | H14: 410030106 | K14: None | L14: 3A01 | M14: FLDS | N14: 1 | T14: 2708_TB | U14: -29535 | V14: =LEFT(H14,3) -> 410
A15: 2708 | F15: 1140 - Revenue X-ray (airlines) | G15: 8R0012 | H15: 410030106 | K15: None | L15: 3A01 | M15: FLDS | N15: 1 | T15: 2708_TB | U15: -952386 | V15: =LEFT(H15,3) -> 410
A16: 2708 | F16: 11400 - Disposals | G16: A425 | H16: 1500140 | K16: None | T16: 2708_TB | U16: -714369 | V16: =LEFT(H16,3) -> 150
A17: 2708 | F17: 1142 - Revenue X-ray (airlines) (outside EU) - GSA | G17: 8R0012 | H17: 410030106 | K17: None | L17: 3A01 | M17: FLDS | N17: 1 | T17: 2708_TB | U17: -2050 | V17: =LEFT(H17,3) -> 410
A18: 2708 | F18: 11450 - Depreciation beginning of the year | G18: A4258 | H18: 1505104 | K18: None | T18: 2708_TB | U18: -1912505 | V18: =LEFT(H18,3) -> 150
A19: 2708 | F19: 1150 - Revenue Trucking DK | G19: 8R0011 | H19: 410010114 | K19: None | L19: 3A01 | M19: FLDS | N19: 1 | T19: 2708_TB | U19: 0 | V19: =LEFT(H19,3) -> 410
A20: 2708 | F20: 11500 - Depreciation | G20: A4258 | H20: 1505104 | K20: None | T20: 2708_TB | U20: -1371693 | V20: =LEFT(H20,3) -> 150
A21: 2708 | F21: 11550 - Depreciation on disposals | G21: A4258 | H21: 1505104 | K21: None | T21: 2708_TB | U21: 465474 | V21: =LEFT(H21,3) -> 150
A22: 2708 | F22: 1160 - Revenue Trucking EU | G22: 8R0011 | H22: 410010114 | K22: None | L22: 3A01 | M22: FLDS | N22: 1 | T22: 2708_TB | U22: 0 | V22: =LEFT(H22,3) -> 410
A23: 2708 | F23: 1170 - Revenue Trucking outside EU | G23: 8R0011 | H23: 410010114 | K23: None | L23: 3A01 | M23: FLDS | N23: 1 | T23: 2708_TB | U23: 0 | V23: =LEFT(H23,3) -> 410
A24: 2708 | F24: 1180 - Revenue Ramphandling | G24: 8R0015 | H24: 410030104 | K24: None | L24: 3A01 | M24: FLDS | N24: 1 | T24: 2708_TB | U24: 0 | V24: =LEFT(H24,3) -> 410
A25: 2708 | F25: 1190 - Revenue Offlinehandling | G25: 8R0013 | H25: 410030103 | K25: None | L25: 3A01 | M25: FLDS | N25: 1 | T25: 2708_TB | U25: -181455 | V25: =LEFT(H25,3) -> 410
A26: 2708 | F26: 12200 - Costs beginning of the year | G26: A410 | H26: 1500200 | K26: None | T26: 2708_TB | U26: 2963381 | V26: =LEFT(H26,3) -> 150
A27: 2708 | F27: 12300 - Additions | G27: A410 | H27: 1500200 | K27: None | T27: 2708_TB | U27: 0 | V27: =LEFT(H27,3) -> 150
A28: 2708 | F28: 12450 - Depreciation beginning of the year | G28: A4108 | H28: 1505200 | K28: None | T28: 2708_TB | U28: -389700 | V28: =LEFT(H28,3) -> 150
A29: 2708 | F29: 12500 - Depreciation | G29: A4108 | H29: 1505200 | K29: None | T29: 2708_TB | U29: -77210 | V29: =LEFT(H29,3) -> 150
A30: 2708 | F30: 1300 - Revenue Rental | G30: 8R0017 | H30: 410080103 | K30: None | L30: 3A01 | M30: FLDS | N30: 1 | T30: 2708_TB | U30: -1254439 | V30: =LEFT(H30,3) -> 410
A31: 2708 | F31: 13200 - Cost beginning of the year | G31: A415 | H31: 1500130 | K31: None | T31: 2708_TB | U31: 807387 | V31: =LEFT(H31,3) -> 150
A32: 2708 | F32: 13300 - Additions | G32: A415 | H32: 1500130 | K32: None | T32: 2708_TB | U32: 463135 | V32: =LEFT(H32,3) -> 150
A33: 2708 | F33: 13400 - Disposals | G33: A415 | H33: 1500130 | K33: None | T33: 2708_TB | U33: -365334 | V33: =LEFT(H33,3) -> 150
A34: 2708 | F34: 13450 - Depreciation beginning of the year | G34: A4158 | H34: 1505103 | K34: None | T34: 2708_TB | U34: -544736 | V34: =LEFT(H34,3) -> 150
A35: 2708 | F35: 1349 - Revenue THC Import EU (service) | G35: 9R00121 | H35: 410010113 | K35: None | L35: 3A01 | M35: FLDS | N35: 1 | T35: 2708_TB | U35: -6711506 | V35: =LEFT(H35,3) -> 410
A36: 2708 | F36: 1350 - Revenue THC Import | G36: 9R00121 | H36: 410010113 | K36: None | L36: 3A01 | M36: FLDS | N36: 1 | T36: 2708_TB | U36: -37957106 | V36: =LEFT(H36,3) -> 410
A37: 2708 | F37: 13500 - Depreciation | G37: A4158 | H37: 1505103 | K37: None | T37: 2708_TB | U37: -152388 | V37: =LEFT(H37,3) -> 150
A38: 2708 | F38: 1351 - Revenue THC Export | G38: 9R00121 | H38: 410010113 | K38: None | L38: 3A01 | M38: FLDS | N38: 1 | T38: 2708_TB | U38: -35646571 | V38: =LEFT(H38,3) -> 410
A39: 2708 | F39: 1352 - Revenue THC Export EU (service) | G39: 9R00121 | H39: 410010113 | K39: None | L39: 3A01 | M39: FLDS | N39: 1 | T39: 2708_TB | U39: -853240 | V39: =LEFT(H39,3) -> 410
A40: 2708 | F40: 13550 - Depreciation on disposals | G40: A4158 | H40: 1505103 | K40: None | T40: 2708_TB | U40: 365334 | V40: =LEFT(H40,3) -> 150
A41: 2708 | F41: 13610 - Cost beginning of the Year SLB | G41: A491 | H41: 1510200 | K41: None | T41: 2708_TB | U41: 196667140 | V41: =LEFT(H41,3) -> 151
A42: 2708 | F42: 13650 - Depreciation beginning of the year SLB | G42: A4918 | H42: 1515200 | K42: None | T42: 2708_TB | U42: -63437102 | V42: =LEFT(H42,3) -> 151
A43: 2708 | F43: 13660 - Depreciation SLB | G43: A4918 | H43: 1515200 | K43: None | T43: 2708_TB | U43: -8967407 | V43: =LEFT(H43,3) -> 151
A44: 2708 | F44: 13685 - Financial cost asset | G44: A525 | H44: 1910500 | K44: None | T44: 2708_TB | U44: 8010000 | V44: =LEFT(H44,3) -> 191
A45: 2708 | F45: 13686 - Financial cost depreciation | G45: A525 | H45: 1910500 | K45: None | T45: 2708_TB | U45: -1592978 | V45: =LEFT(H45,3) -> 191
A46: 2708 | F46: 13691 - Cost the beginning of the year | G46: A492 | H46: 1510101 | K46: None | T46: 2708_TB | U46: 15265695 | V46: =LEFT(H46,3) -> 151
A47: 2708 | F47: 13694 - Depreciatins beginning of the year | G47: A4928 | H47: 1515101 | K47: None | T47: 2708_TB | U47: -1957286 | V47: =LEFT(H47,3) -> 151
A48: 2708 | F48: 13695 - Depreciations | G48: A4928 | H48: 1515101 | K48: None | T48: 2708_TB | U48: -2740200 | V48: =LEFT(H48,3) -> 151
A49: 2708 | F49: 1370 - Revenue Pharma | G49: 9R00121 | H49: 410010113 | K49: None | L49: 3A01 | M49: FLDS | N49: 1 | T49: 2708_TB | U49: -5664453 | V49: =LEFT(H49,3) -> 410
A50: 2708 | F50: 1371 - Revenue Pharma EU (service) | G50: 9R00121 | H50: 410010113 | K50: None | L50: 3A01 | M50: FLDS | N50: 1 | T50: 2708_TB | U50: 0 | V50: =LEFT(H50,3) -> 410
A51: 2708 | F51: 1400 - Revenue other | G51: 8R0020 | H51: 410080104 | K51: None | L51: 3A01 | M51: FLDS | N51: 1 | T51: 2708_TB | U51: -4273 | V51: =LEFT(H51,3) -> 410
A52: 2708 | F52: 1410 - Service Continuity | G52: 9R00121 | H52: 410010113 | K52: None | L52: 3A01 | M52: FLDS | N52: 1 | T52: 2708_TB | U52: -2034040 | V52: =LEFT(H52,3) -> 410
A53: 2708 | F53: 14100 - Inventory | G53: A605 | H53: 1300101 | K53: None | T53: 2708_TB | U53: 538793 | V53: =LEFT(H53,3) -> 130
A54: 2708 | F54: 1411 - Storage export + airlines | G54: 9R00122 | H54: 410010112 | K54: None | L54: 3A01 | M54: FLDS | N54: 1 | T54: 2708_TB | U54: -6482323 | V54: =LEFT(H54,3) -> 410
A55: 2708 | F55: 1412 - Storage import | G55: 9R00122 | H55: 410010112 | K55: None | L55: 3A01 | M55: FLDS | N55: 1 | T55: 2708_TB | U55: -8637279 | V55: =LEFT(H55,3) -> 410
A56: 2708 | F56: 1420 - Rebates | G56: 8R0021 | H56: 410070101 | K56: None | L56: 3A01 | M56: FLDS | N56: 1 | T56: 2708_TB | U56: 1476221 | V56: =LEFT(H56,3) -> 410
A57: 2708 | F57: 1450 - CC Shipments | G57: 9R00121 | H57: 410010113 | K57: None | L57: 3A01 | M57: FLDS | N57: 1 | T57: 2708_TB | U57: -12099 | V57: =LEFT(H57,3) -> 410
A58: 2708 | F58: 1451 - CC Shipments | G58: 9R00121 | H58: 410010113 | K58: None | L58: 3A01 | M58: FLDS | N58: 1 | T58: 2708_TB | U58: 0 | V58: =LEFT(H58,3) -> 410
A59: 2708 | F59: 1460 - CC Shipments | G59: 9R00121 | H59: 410010113 | K59: None | L59: 3A01 | M59: FLDS | N59: 1 | T59: 2708_TB | U59: 12099 | V59: =LEFT(H59,3) -> 410
A60: 2708 | F60: 1500 - K24/28 Revenue Exports FFH - DK | G60: 8R0020 | H60: 410080104 | K60: None | L60: 3A01 | M60: FLDS | N60: 1 | T60: 2708_TB | U60: -1313438 | V60: =LEFT(H60,3) -> 410
A61: 2708 | F61: 1510 - K24/28 Cross Docking | G61: 8R0020 | H61: 410080104 | K61: None | L61: 3A01 | M61: FLDS | N61: 1 | T61: 2708_TB | U61: -214249 | V61: =LEFT(H61,3) -> 410
A62: 2708 | F62: 15100 - Accounts receivables | G62: A625 | H62: 1200103 | K62: None | T62: 2708_TB | U62: 35596972 | V62: =LEFT(H62,3) -> 120
A63: 2708 | F63: 1511 - K24/28 WB Incentive crossdocking | G63: 8R0020 | H63: 410080104 | K63: None | L63: 3A01 | M63: FLDS | N63: 1 | T63: 2708_TB | U63: 57972 | V63: =LEFT(H63,3) -> 410
A64: 2708 | F64: 15125 - Revenue not yet invoiced | G64: A630 | H64: 1200604 | K64: None | T64: 2708_TB | U64: 11284152 | V64: =LEFT(H64,3) -> 120
A65: 2708 | F65: 15150 - Bad debts reserve | G65: A6259 | H65: 1200103 | K65: None | T65: 2708_TB | U65: -2635368 | V65: =LEFT(H65,3) -> 120
A66: 2708 | F66: 1520 - K24/28 AVI - Day Old Chicks | G66: 8R0020 | H66: 410080104 | K66: None | L66: 3A01 | M66: FLDS | N66: 1 | T66: 2708_TB | U66: -637235 | V66: =LEFT(H66,3) -> 410
A67: 2708 | F67: 15230 - Other receivables | G67: A690 | H67: 1200103 | K67: None | T67: 2708_TB | U67: 387949 | V67: =LEFT(H67,3) -> 120
A68: 2708 | F68: 15250 - Employee receivables | G68: A690 | H68: 1200103 | K68: None | T68: 2708_TB | U68: 10320 | V68: =LEFT(H68,3) -> 120
A69: 2708 | F69: 1530 - K24/28 Imports FFH - DK | G69: 8R0020 | H69: 410080104 | K69: None | L69: 3A01 | M69: FLDS | N69: 1 | T69: 2708_TB | U69: -179777 | V69: =LEFT(H69,3) -> 410
A70: 2708 | F70: 15300 - Prepaid expenses | G70: A640 | H70: 1400100 | K70: None | T70: 2708_TB | U70: 964208 | V70: =LEFT(H70,3) -> 140
A71: 2708 | F71: 15361 - Recharge provision - A630 | G71: A630 | H71: 1200604 | K71: None | T71: 2708_TB | U71: 1243974 | V71: =LEFT(H71,3) -> 120
A72: 2708 | F72: 15370 - Loan WFS Holding SA - A545 | G72: A545 | H72: 1201401 | K72: None | T72: 2708_TB | U72: 172493249 | V72: =LEFT(H72,3) -> 120
A73: 2708 | F73: 15371 - Interests loan WFS Holding SA - A546 | G73: A546 | H73: 1201301 | K73: None | T73: 2708_TB | U73: 49443747 | V73: =LEFT(H73,3) -> 120
A74: 2708 | F74: 1540 - K24/28 Charterflights (AID) | G74: 8R0020 | H74: 410080104 | K74: None | L74: 3A01 | M74: FLDS | N74: 1 | T74: 2708_TB | U74: -207904 | V74: =LEFT(H74,3) -> 410
A75: 2708 | F75: 15400 - Deposits | G75: A690 | H75: 1200103 | K75: None | T75: 2708_TB | U75: 1598755 | V75: =LEFT(H75,3) -> 120
A76: 2708 | F76: 15600 - Deferred tax assets | G76: A705 | H76: 1800100 | K76: None | T76: 2708_TB | U76: 38236088 | V76: =LEFT(H76,3) -> 180
A77: 2708 | F77: 15700 - Prepaid tax | G77: A680 | H77: 1200903 | K77: None | T77: 2708_TB | U77: 5754000 | V77: =LEFT(H77,3) -> 120
A78: 2708 | F78: 1600 - Reinvoicing | G78: 8R0020 | H78: 410080104 | K78: None | L78: 3A01 | M78: FLDS | N78: 1 | T78: 2708_TB | U78: 0 | V78: =LEFT(H78,3) -> 410
A79: 2708 | F79: 16100 - Petty cash | G79: A825 | H79: 1101000 | K79: None | T79: 2708_TB | U79: 33049 | V79: =LEFT(H79,3) -> 110
A80: 2708 | F80: 16200 - Nordea 7557 632 195 | G80: A825 | H80: 1101000 | K80: None | T80: 2708_TB | U80: 30300144 | V80: =LEFT(H80,3) -> 110
A81: 2708 | F81: 16230 - Nordea 9033 176 195 Kantinedrift | G81: A825 | H81: 1101000 | K81: None | T81: 2708_TB | U81: 154964 | V81: =LEFT(H81,3) -> 110
A82: 2708 | F82: 20050 - Share capital | G82: P000 | H82: 3100100 | K82: None | T82: 2708_TB | U82: -502000 | V82: =LEFT(H82,3) -> 310
A83: 2708 | F83: 20060 - Profit/loss carried forward | G83: P010 | H83: 3500200 | K83: None | T83: 2708_TB | U83: -104209670 | V83: =LEFT(H83,3) -> 350
A84: 2708 | F84: 2100 - Raw material. supplies and goo | G84: 8R0620FD | H84: 501180101 | K84: None | L84: 3A01 | M84: FLDS | N84: 1 | T84: 2708_TB | U84: 2651110 | V84: =LEFT(H84,3) -> 501
A85: 2708 | F85: 2150 - Sub-contracting (x-ray) | G85: 8R0430FD | H85: 506010101 | K85: None | L85: 3A01 | M85: FLDS | N85: 1 | T85: 2708_TB | U85: 3119501 | V85: =LEFT(H85,3) -> 506
A86: 2708 | F86: 2250 - Trucking subcontracting | G86: 8R0420FD | H86: 506010106 | K86: None | L86: 3A01 | M86: FLDS | N86: 1 | T86: 2708_TB | U86: 319980 | V86: =LEFT(H86,3) -> 506
A87: 2708 | F87: 22500 - Financial leasing debt SLB | G87: P585 | H87: 2710200 | K87: None | T87: 2708_TB | U87: -299195580 | V87: =LEFT(H87,3) -> 271
A88: 2708 | F88: 2252 - K24/28 - Costs Day Old Chicks | G88: 8R0410FD | H88: 506010105 | K88: None | L88: 3A01 | M88: FLDS | N88: 1 | T88: 2708_TB | U88: 613793 | V88: =LEFT(H88,3) -> 506
A89: 2708 | F89: 2260 - Handling subcontracting | G89: 8R0410FD | H89: 506010105 | K89: None | L89: 3A01 | M89: FLDS | N89: 1 | T89: 2708_TB | U89: 77422 | V89: =LEFT(H89,3) -> 506
A90: 2708 | F90: 22600 - Financial leasing debt. solar pannels | G90: P585 | H90: 2710200 | K90: None | T90: 2708_TB | U90: -11018407 | V90: =LEFT(H90,3) -> 271
A91: 2708 | F91: 2290 - Ramp handling | G91: 8R0440FD | H91: 506010105 | K91: None | L91: 3A01 | M91: FLDS | N91: 1 | T91: 2708_TB | U91: 375903 | V91: =LEFT(H91,3) -> 506
A92: 2708 | F92: 2300 - Other Cost of Sales | G92: 8R0440FD | H92: 506010105 | K92: None | L92: 3A01 | M92: FLDS | N92: 1 | T92: 2708_TB | U92: 206362 | V92: =LEFT(H92,3) -> 506
A93: 2708 | F93: 23100 - Sales VAT | G93: P690 | H93: 2100706 | K93: None | T93: 2708_TB | U93: -2796374 | V93: =LEFT(H93,3) -> 210
A94: 2708 | F94: 23150 - EU goods VAT | G94: P690 | H94: 2100706 | K94: None | T94: 2708_TB | U94: -32751 | V94: =LEFT(H94,3) -> 210
A95: 2708 | F95: 23170 - EU services VAT | G95: P690 | H95: 2100706 | K95: None | T95: 2708_TB | U95: -934396 | V95: =LEFT(H95,3) -> 210
A96: 2708 | F96: 23190 - IT VAT | G96: P690 | H96: 2100706 | K96: None | T96: 2708_TB | U96: 0 | V96: =LEFT(H96,3) -> 210
A97: 2708 | F97: 23200 - Purchase VAT | G97: P690 | H97: 2100706 | K97: None | T97: 2708_TB | U97: 2063120 | V97: =LEFT(H97,3) -> 210
A98: 2708 | F98: 23400 - Energy tax | G98: P690 | H98: 2100706 | K98: None | T98: 2708_TB | U98: 122788 | V98: =LEFT(H98,3) -> 210
A99: 2708 | F99: 23900 - VAT payable | G99: P690 | H99: 2100706 | K99: None | T99: 2708_TB | U99: 0 | V99: =LEFT(H99,3) -> 210
A100: 2708 | F100: 24100 - Accounts payable | G100: P610 | H100: 2100104 | K100: None | T100: 2708_TB | U100: -4453899 | V100: =LEFT(H100,3) -> 210
...

Sheet ERP TO OS MAPPING
A1: Local COA | B1: OS Mapping
A2: 10065 - Additions | B2: 1521300
A3: 10075 - Depreciation beginning of the year | B3: 1525300
A4: 1100 - Revenue Cargo DK Import | B4: 410010102
A5: 1101 - Revenue Cargo DK Export | B5: 410010104
A6: 1110 - Revenue Cargo EU (services) Im | B6: 410010102
A7: 1111 - Revenue Cargo EU (service) Exp | B7: 410010104
A8: 1120 - Revenue Cargo outside EU (C) I | B8: 410010102
A9: 11200 - Costs beginning of the year | B9: 1500140
A10: 1121 - Revenue Cargo outside EU (C) E | B10: 410010104
A11: 1122 - Revenue Cargo outside EU Export - GSA | B11: 410010104
A12: 1130 - Revenue X-ray (forwarders) | B12: 410030106
A13: 11300 - Additions | B13: 1500140
... A524: 9210 - Reg. tax prior years | B524: 607100101

Sheet OS to BFC L2 Mapping
A1: WFS ACCNT | B1: OS Level 2 Mapping
A3: 9R0010 | B3: 4100000 - Revenue
A4: 9R0011 | B4: 4100000 - Revenue
A5: 9R00121 | B5: 4100000 - Revenue
A6: 9R00122 | B6: 4100000 - Revenue
A7: 9R0013 | B7: 4100000 - Revenue
A8: 9R0014 | B8: 4100000 - Revenue
A9: 8R0010
A10: 8R0011 | B10: 4100000 - Revenue
A11: 8R0012 | B11: 4100000 - Revenue
A12: 8R0013 | B12: 4100000 - Revenue
A13: 8R0014 | B13: 4100000 - Revenue
A14: 8R0015 | B14: 4100000 - Revenue
A15: 8R0016 | B15: 4100000 - Revenue
A16: 8R0017 | B16: 4100000 - Revenue
A17: 8R0018 | B17: 4100000 - Revenue
A18: 8R0019 | B18: 4100000 - Revenue
A19: 8R0020 | B19: 4100000 - Revenue
A20: 8R0021 | B20: 4100000 - Revenue
A21: 7R0000
A23: 9R1110FD | B23: 5020000 - Staff Costs
A24: 9R1120FD | B24: 5020000 - Staff Costs
A25: 9R1130FD | B25: 5020000 - Staff Costs
A26: 9R1135FD | B26: 5020000 - Staff Costs
A27: 9R1140FD | B27: 5020000 - Staff Costs
A28: 9R1150FD | B28: 5020000 - Staff Costs
A29: 9R1210FD | B29: 5020000 - Staff Costs
A30: 9R1220FD | B30: 5020000 - Staff Costs
A31: 9R1230FD | B31: 5020000 - Staff Costs
A32: 8R0130FD | B32: 5020000 - Staff Costs
A33: 8R0140FD | B33: 5020000 - Staff Costs
A34: 9R1510FD | B34: 5020000 - Staff Costs
A35: 9R1520FD | B35: 5020000 - Staff Costs
A36: 7R0010FD
A37: 7R0020FD | B37: 5020000 - Staff Costs
A38: 7R0030FD | B38: 5020000 - Staff Costs
A39: 9R1510FD | B39: 5060000 - Subcontracting services
A40: 9R1520FD | B40: 5060000 - Subcontracting services
A41: 8R0410FD | B41: 5060000 - Subcontracting services
A42: 8R0420FD | B42: 5060000 - Subcontracting services
A43: 8R0430FD | B43: 5060000 - Subcontracting services
A44: 8R0440FD | B44: 5060000 - Subcontracting services
A45: 8R0450FD | B45: 5060000 - Subcontracting services
A46: 8R0460FD | B46: 5060000 - Subcontracting services
A47: 7R0040FD
A48: 8R0510FD | B48: 5080000 - Other costs
A49: 8R0520FD | B49: 5080000 - Other costs
A50: 7R0050FD
A51: 8R0610FD | B51: 5050000 - Company Premise Utilities And Maintenance
A52: 8R0620FD | B52: 5010000 - Cost Of Raw Materials And Supplies
A53: 8R0630FD | B53: 5080000 - Other costs
A54: 8R0640FD | B54: 5080000 - Other costs
A55: 8R0650FD | B55: 5080000 - Other costs
A56: 8R0660FD | B56: 5080000 - Other costs
A57: 8R0670FD | B57: 5080000 - Other costs
A58: 7R0060FD
A59: 8R0710FD | B59: 5050000 - Company Premise Utilities And Maintenance
A60: 8R0720FD | B60: 5050000 - Company Premise Utilities And Maintenance
A61: 8R0730FD | B61: 5050000 - Company Premise Utilities And Maintenance
A62: 8R0740FD | B62: 5050000 - Company Premise Utilities And Maintenance
A63: 8R0760FD | B63: 5050000 - Company Premise Utilities And Maintenance
A64: 9R0752FD | B64: 5050000 - Company Premise Utilities And Maintenance
A65: 9R0753FD | B65: 5050000 - Company Premise Utilities And Maintenance
A66: 9R0751FD | B66: 5050000 - Company Premise Utilities And Maintenance
A67: 7R0070FD
A68: 8R0810FD | B68: 5050000 - Company Premise Utilities And Maintenance
A69: 8R0820FD | B69: 5080000 - Other costs
A70: 8R0830FD | B70: 5050000 - Company Premise Utilities And Maintenance
A71: 8R0840FD | B71: 5050000 - Company Premise Utilities And Maintenance
A72: 8R0850FD | B72: 5050000 - Company Premise Utilities And Maintenance
A73: 8R0860FD | B73: 5050000 - Company Premise Utilities And Maintenance
A74: 7R0080FD
A75: 7R0090FD | B75: 5050000 - Company Premise Utilities And Maintenance
A76: 7R0100FD | B76: 5030000 - Licence Fees
A77: 8R1110FD | B77: 5080000 - Other costs
A78: 8R1120FD | B78: 5080000 - Other costs
A79: 8R1130FD | B79: 5080000 - Other costs
A80: 8R1140FD | B80: 5080000 - Other costs
A81: 7R0110FD
A82: 8R1250FD | B82: 5080000 - Other costs
A83: 8R1260FD | B83: 5080000 - Other costs
A84: 7R0120FD
A85: 8R1350FD | B85: 5080000 - Other costs
A86: 7R0130FD
A87: 9R3610FD | B87: 5080000 - Other costs
A88: 9R3620FD | B88: 5080000 - Other costs
A89: 9R3710FD | B89: 5080000 - Other costs
A90: 9R3720FD | B90: 5080000 - Other costs
A91: 7R0131FD
A92: 8R1505FD
A94: 7R0152FD | B94: 5080000 - Other costs
A95: 7R0151FD | B95: 5080000 - Other costs
A96: 7R0155FD | B96: 5080000 - Other costs
A97: 7R0160FD | B97: 5080000 - Other costs
A98: 7R0170FD | B98: 5080000 - Other costs
A99: 5R2000
A100: 5R1000
A102: 6R0000A
A103: 4R9000
A105: 7R0020OH | B105: 5020000 - Staff Costs
...
